{
  "object_identity": {
    "schema_version": 2,
    "object_type": "nav_context_annotation",
    "nav_context_key": "way/271982170@node/12598724573/forward",
    "nav_segment_key": "way/271982170",
    "context_scope": "intersection_approach",
    "applies_to_intersection_key": "node/12598724573",
    "approach_direction": "forward",
    "source_osm": {
      "osm_type": "way",
      "osm_id": 271982170
    },
    "split_index": 0
  },
  "osm_reference": {
    "osm_selected_tags": {
      "highway": "secondary",
      "name": "鳳楠路",
      "oneway": "yes",
      "lanes": "3"
    },
    "map_links": {
      "openstreetmap": "https://www.openstreetmap.org/way/271982170",
      "google_maps": "https://www.google.com/maps/@22.7267865,120.3291276,19z"
    },
    "nearby_intersections": [
      {
        "nav_intersection_key": "node/12598724570",
        "osm_id": 12598724570,
        "intersection_name": "楠陽路 / 鳳楠路",
        "connected_way_count": 4,
        "connected_ways": [
          {
            "osm_way_id": 23787579,
            "name": "楠陽路",
            "highway": "tertiary"
          },
          {
            "osm_way_id": 268219240,
            "name": "楠陽路",
            "highway": "tertiary"
          },
          {
            "osm_way_id": 268219247,
            "name": "鳳楠路",
            "highway": "secondary"
          },
          {
            "osm_way_id": 271982170,
            "name": "鳳楠路",
            "highway": "secondary"
          }
        ],
        "road_classes": [
          "secondary",
          "tertiary"
        ],
        "candidate_priority": 140,
        "manual_targets": [
          "check_intersection_geometry",
          "check_lane_movements"
        ],
        "coordinate": {
          "lng": 120.3301755,
          "lat": 22.724145
        },
        "map_links": {
          "openstreetmap": "https://www.openstreetmap.org/node/12598724570",
          "google_maps": "https://www.google.com/maps/@22.724145,120.3301755,20z"
        },
        "distance_m": 0
      },
      {
        "nav_intersection_key": "node/12598724577",
        "osm_id": 12598724577,
        "intersection_name": "建楠路 / 鳳楠路",
        "connected_way_count": 4,
        "connected_ways": [
          {
            "osm_way_id": 27527295,
            "name": "鳳楠路",
            "highway": "residential"
          },
          {
            "osm_way_id": 271982140,
            "name": "建楠路",
            "highway": "tertiary"
          },
          {
            "osm_way_id": 271982144,
            "name": "建楠路",
            "highway": "tertiary"
          },
          {
            "osm_way_id": 271982170,
            "name": "鳳楠路",
            "highway": "secondary"
          }
        ],
        "road_classes": [
          "residential",
          "secondary",
          "tertiary"
        ],
        "candidate_priority": 140,
        "manual_targets": [
          "check_intersection_geometry",
          "check_lane_movements"
        ],
        "coordinate": {
          "lng": 120.3291276,
          "lat": 22.7267865
        },
        "map_links": {
          "openstreetmap": "https://www.openstreetmap.org/node/12598724577",
          "google_maps": "https://www.google.com/maps/@22.7267865,120.3291276,20z"
        },
        "distance_m": 0
      },
      {
        "nav_intersection_key": "node/12598724573",
        "osm_id": 12598724573,
        "intersection_name": "朝明路 / 鳳楠路",
        "connected_way_count": 2,
        "connected_ways": [
          {
            "osm_way_id": 216735440,
            "name": "朝明路",
            "highway": "residential"
          },
          {
            "osm_way_id": 271982170,
            "name": "鳳楠路",
            "highway": "secondary"
          }
        ],
        "road_classes": [
          "residential",
          "secondary"
        ],
        "candidate_priority": 124,
        "manual_targets": [
          "check_intersection_geometry",
          "check_lane_movements"
        ],
        "coordinate": {
          "lng": 120.3294734,
          "lat": 22.7254988
        },
        "map_links": {
          "openstreetmap": "https://www.openstreetmap.org/node/12598724573",
          "google_maps": "https://www.google.com/maps/@22.7254988,120.3294734,20z"
        },
        "distance_m": 0
      },
      {
        "nav_intersection_key": "node/2985906105",
        "osm_id": 2985906105,
        "intersection_name": "鳳楠路",
        "connected_way_count": 2,
        "connected_ways": [
          {
            "osm_way_id": 271982170,
            "name": "鳳楠路",
            "highway": "secondary"
          },
          {
            "osm_way_id": 294950912,
            "name": null,
            "highway": "residential"
          }
        ],
        "road_classes": [
          "residential",
          "secondary"
        ],
        "candidate_priority": 106,
        "manual_targets": [
          "check_intersection_geometry",
          "check_lane_movements"
        ],
        "coordinate": {
          "lng": 120.3292549,
          "lat": 22.7262983
        },
        "map_links": {
          "openstreetmap": "https://www.openstreetmap.org/node/2985906105",
          "google_maps": "https://www.google.com/maps/@22.7262983,120.3292549,20z"
        },
        "distance_m": 0
      }
    ]
  },
  "lane_nav_tags": {
    "osm_review_tags": {
      "osm_lane_status": "not_checked",
      "osm_turn_lane_status": "not_checked",
      "osm_motorcycle_status": "not_checked",
      "osm_review_note": null
    },
    "taiwan_motorcycle_tags": {
      "movement_rules": [
        {
          "movement_key": "way/271982170@node/12598724573/forward->way/216735440/uturn",
          "from_context_key": "way/271982170@node/12598724573/forward",
          "to_segment_key": "way/216735440",
          "applies_to_intersection_key": "node/12598724573",
          "approach_segment_key": "way/271982170",
          "selected_road": "鳳楠路",
          "approach_direction": "forward",
          "movement": "uturn",
          "target_road": "朝明路",
          "vehicle_rule": "normal",
          "motorcycle_turn_rule": "two_stage_optional",
          "two_stage_sign_exists": "unknown",
          "waiting_zone_exists": "yes",
          "waiting_zone_position": "front_right",
          "data_origin": "context_v2"
        }
      ]
    },
    "offset_relations": [],
    "lane_detail_tags": {
      "lane_profiles": []
    }
  },
  "geometry": {
    "type": "LineString",
    "coordinates": [
      [
        120.3291276,
        22.7267865
      ],
      [
        120.3291371,
        22.7267143
      ],
      [
        120.3291525,
        22.72666
      ],
      [
        120.3292549,
        22.7262983
      ],
      [
        120.3294367,
        22.7256328
      ],
      [
        120.3294474,
        22.7255938
      ],
      [
        120.3294734,
        22.7254988
      ],
      [
        120.3295308,
        22.7253659
      ],
      [
        120.3297832,
        22.7247812
      ],
      [
        120.3300745,
        22.7243087
      ],
      [
        120.3301005,
        22.7242665
      ],
      [
        120.3301755,
        22.724145
      ]
    ]
  },
  "annotation_metadata": {
    "created_from": "manual_form",
    "evidence_type": "streetview",
    "manual_verified": "yes",
    "verified_by": "anna",
    "verified_at": "2026-07-16T11:00",
    "verified_at_precision": "hour",
    "verified_timezone": "Asia/Taipei",
    "confidence": "medium",
    "note": ""
  }
}
